mindfree/__init__.py
mind_free-0.5.dist-info/METADATA
mind_free-0.5.dist-info/WHEEL
mind_free-0.5.dist-info/top_level.txt
mind_free-0.5.dist-info/RECORD
