Metadata-Version: 2.1
Name: mind-free
Version: 0.5
Summary: Mind free, a usefull package to handle simple bits
Home-page: UNKNOWN
Author: Joel Dangmei
Author-email: UNKNOWN
License: UNKNOWN
Platform: UNKNOWN
